{
  "_id": 373909,
  "id": "fluffy_alpaca_sheriff",
  "rarity": 3,
  "name": "「绵绵警官」",
  "description": "以外表温顺腼腆的绵驮兽为原型制作的纸板模型，若将它放置入一群不大爱动的真绵驮兽中，甚至也能以假乱真。\\n「绵绵警官」对大部分的人类都十分友好，脾气就像身上的绒毛一样柔软——但如果你是坏人，那可要当心了，它的飞踢可是非常厉害的！",
  "load": 60,
  "energy": 60,
  "exp": 60,
  "category": [
    {
      "id": 7015,
      "category": "特别物件",
      "type": "Exterior"
    }
  ],
  "recipe": [
    {
      "_id": 101325,
      "id": "flammabomb_wood",
      "name": "燃爆木",
      "amount": 6
    },
    {
      "_id": 101001,
      "id": "iron_chunk",
      "name": "铁块",
      "amount": 2
    }
  ]
}
