{
  "id": "foundations_of_stone_fortunate_times",
  "originalId": 372107,
  "rarity": 3,
  "name": "铸石地基-「运开时泰」",
  "description": "由坚密的石材拼接而成的地板，石板的排布紧密，常用于广场和码头等人流量较大的场所。\\n光洁而坚硬的石材应用了璃月的传统工艺，熔铸碎石与沙粒制成，牢固耐用，造价低廉，并因此远销至大陆各国。\\n在璃月港的一些传说中，「地面」、「土地」和「运势」有着密切的联系。若是城镇的地面长期完好，则有着前路顺畅无阻的寓意。因此，对地面的维护至关重要。「海灯节」等重要的庆典通常也会在铺设了这类地板的场所举行。",
  "load": 35,
  "energy": 60,
  "exp": 60,
  "category": [
    {
      "id": 10001,
      "category": "山体",
      "type": "Exterior"
    }
  ],
  "recipe": [
    {
      "id": "white_iron_chunk",
      "name": "白铁块",
      "amount": 8
    }
  ]
}
