{
  "_id": 374322,
  "id": "tea_village_stone_table_cultured_leisure",
  "rarity": 3,
  "name": "茶庄石桌-「悠雅闲趣」",
  "description": "外形古雅的石制圆桌，表面雕有朴素但精美的花纹，能在翘英庄内见到。\\n据说，在璃月的庭院设计中，青石被视为与自然和谐相融的象征，而圆桌则象征着抒怀娴静。故此在沉玉谷，人们喜欢用圆形石桌装点庭院，不仅是为了方便品茗畅谈，更寄寓了修身养性和磨砺心志之意。",
  "load": 24,
  "energy": 60,
  "exp": 60,
  "category": [
    {
      "id": 7002,
      "category": "桌子",
      "type": "Exterior"
    }
  ],
  "recipe": [
    {
      "_id": 101001,
      "id": "iron_chunk",
      "name": "铁块",
      "amount": 12
    }
  ]
}
