{
  "_id": 332059,
  "id": "an_adventure_through_the_morning_mist",
  "shareId": 554,
  "name": "「穿越晨靄的冒險」",
  "title": "「穿越晨靄的冒險」",
  "desc": "「…我不會讓你得到它的，因為我們會在這裡終結你的計畫！」",
  "in_play_description": "",
  "attributes": {
    "cost": 0,
    "card_type": "事件牌",
    "energy": []
  },
  "skills": [
    {
      "name": "",
      "desc": "將費用最低的至多2張手牌置入牌組底，然後抽等量的牌。<br/><span style=\"color:#FFFFFFFF\">此牌被<span style=\"color:#FFFFFFFF\">捨棄</span>後：</span><span style=\"color:#FFFFFFFF\"><span style=\"color:#FFFFFFFF\">冒險</span></span>1次。"
    }
  ]
}
