{
  "_id": 2605,
  "id": "experimental_field_generator",
  "shareId": 586,
  "name": "Experimental Field Generator",
  "title": "Unfinished Ideal: Experimental Field Generator",
  "desc": "A product of the Fontaine Research Institute of Kinetic Energy Engineering that has gone out of control due to an accident. It has the ability to \"counteract\" the effects of gravity.",
  "attributes": {
    "hp": 11,
    "card_type": "Character Card",
    "energy": 2,
    "element": "Geo",
    "weapon": "Other Weapons",
    "faction": [
      "Monster"
    ],
    "source": "Reward for accepting the Tavern Challenge at The Cat's Tail and claiming victory in a Friendly Fracas with Experimental Field Generator"
  },
  "skills": [
    {
      "id": "gravity_application_crush",
      "name": "Gravity Application: Crush",
      "desc": "Deals ? ?.",
      "skillTag": [
        "Normal Attack"
      ],
      "points": [
        {
          "_id": 1106,
          "id": "geo",
          "type": "Geo",
          "count": 1
        },
        {
          "_id": 1109,
          "id": "unaligned_element",
          "type": "Unaligned Element",
          "count": 2
        }
      ]
    },
    {
      "id": "gravity_application_point_null",
      "name": "Gravity Application: Point Null",
      "desc": "Deal ? ? and generate 2 stacks of <span style=\"color:#FFFFFFFF\">Efficient Switch</span>.",
      "skillTag": [
        "Elemental Skill"
      ],
      "points": [
        {
          "_id": 1106,
          "id": "geo",
          "type": "Geo",
          "count": 3
        }
      ]
    },
    {
      "id": "gravity_application_field_reduction",
      "name": "Gravity Application: Field Reduction",
      "desc": "Deal ? ?, as well as generate <span style=\"color:#FFFFFFFF\">Low Gravity Background</span> and <span style=\"color:#FFFFFFFF\">Shock Blast</span>. During this Round, all your characters on standby use 1 less <span style=\"color:#FFFFFFFF\">Unaligned Element</span> when using their next <span style=\"color:#FFFFFFFF\">Normal Attack</span>.",
      "skillTag": [
        "Elemental Burst"
      ],
      "points": [
        {
          "_id": 1106,
          "id": "geo",
          "type": "Geo",
          "count": 3
        },
        {
          "_id": 1110,
          "id": "energy",
          "type": "Energy",
          "count": 2
        }
      ]
    }
  ]
}
