{
  "_id": 312027,
  "id": "amethyst_crown",
  "shareId": 356,
  "name": "Аметистовый венец",
  "title": "Глубинный союз: Аметистовый венец",
  "desc": "«В честь вечного оазиса и распускающихся падисар Повелительница цветов надела аметистовую корону».",
  "in_play_description": "<span style=\"color:#FFFFFFFF\">Когда персонаж с этой картой является активным персонажем, а противник получает <span style=\"color:#7EC236FF\">Дендро урон</span>:</span> накапливается 1 <span style=\"color:#FFFFFFFF\">Кристальный венок</span>. Если ваше кол-во <span style=\"color:#FFFFFFFF\">венков</span> равно числу карт в вашей руке или больше, вы получаете 1 случайный дайс базового элемента.<br/>За один раунд можно получить не более 2 дайсов.",
  "attributes": {
    "cost": 1,
    "cost_type": "Совпадающий элемент",
    "card_type": "Карты экипировки",
    "energy": [
      {
        "_id": 1108,
        "id": "matching_element",
        "type": "Совпадающий элемент",
        "count": 1
      }
    ],
    "tags": ["Артефакт"]
  },
  "skills": [
    {
      "name": "",
      "desc": "<span style=\"color:#FFFFFFFF\">Когда персонаж с этой картой является активным персонажем, а противник получает <span style=\"color:#7EC236FF\">Дендро урон</span>:</span> накапливается 1 <span style=\"color:#FFFFFFFF\">Кристальный венок</span>. Если ваше кол-во <span style=\"color:#FFFFFFFF\">венков</span> равно числу карт в вашей руке или больше, вы получаете 1 случайный дайс базового элемента.<br/>За один раунд можно получить не более 2 дайсов.<br/>Персонаж может экипировать только 1 артефакт."
    }
  ]
}
