{
  "_id": 370817,
  "id": "courtyard_pavilion_amidst_the_rivers",
  "rarity": 4,
  "name": "Садовый павильон: Среди тысячи вод",
  "description": "Павильон, украшенный плиткой цвета индиго, замысловатым золотым узором и каменными колоннами с затейливой резьбой. Все элементы декора идеально сочетаются друг с другом, благодаря чему павильон выглядит красиво и гармонично. Учитывая, что в дизайне приусадебных садов Фонтейна в качестве основных декоративных элементов зачастую используются ручьи или фонтаны, обычный павильон в отражённом от воды свете может показаться слишком ярким и слепящим. Однако павильон, выполненный из натурального камня, при таком освещении смотрится ярко, но гармонично и приятно для глаза.",
  "load": 193,
  "energy": 90,
  "exp": 90,
  "category": [
    {
      "id": 13006,
      "category": "Стиль Фонтейна"
    }
  ],
  "recipe": [
    {
      "_id": 101002,
      "id": "white_iron_chunk",
      "name": "Обломок белого железа",
      "amount": 12
    },
    {
      "_id": 101404,
      "id": "blue_dye",
      "name": "Синяя краска",
      "amount": 6
    }
  ]
}
