{
  "_id": 371146,
  "id": "evenhanded_judgment",
  "rarity": 4,
  "name": "Беспристрастный суд",
  "description": "Модель воздушного шара из мягкой ткани с просторной корзиной, напоминающая шары над стадионом Священного пламени.\\nГоворят, что все новые судьи, прежде чем их признают способными самостоятельно вести дела, проходят практику на таких шарах. С высоты открывается лучший вид на соревнования. Естественно, не все могут легко преодолеть страх высоты, а поэтому новые судьи Потомков Крон и клана Цветочного Пера чаще успешно проходят стажировку, чем другие...",
  "load": 580,
  "energy": 90,
  "exp": 90,
  "category": [
    {
      "id": 6003,
      "category": "Крупные украшения",
      "type": "Exterior"
    }
  ],
  "recipe": [
    {
      "_id": 101324,
      "id": "ashen_aratiku_wood",
      "name": "Древесина пепельного аратику",
      "amount": 8
    },
    {
      "_id": 101401,
      "id": "fabric",
      "name": "Ткань",
      "amount": 10
    },
    {
      "_id": 101404,
      "id": "blue_dye",
      "name": "Синяя краска",
      "amount": 6
    }
  ]
}