{
  "_id": 374502,
  "id": "foundations_of_stone_timely_arrival",
  "rarity": 3,
  "name": "Основание из камня: Своевременное прибытие",
  "description": "Пол из каменных плит, аккуратно уложенных вплотную друг к другу. Его можно укладывать разными способами, а также использовать для мощения дорог, по которым не будут перевозить тяжёлые грузы. Полированный и закалённый камень изготавливается с использованием традиционной техники Ли Юэ, при которой камни дробят и смешивают с песком. Разветвлённая сеть дорог не только является необходимым условием для развития торговли, но и предоставляет возможности для людей, живущих в отдалённых местах.",
  "load": 35,
  "energy": 60,
  "exp": 60,
  "category": [
    {
      "id": 7012,
      "category": "Земли",
      "type": "Exterior"
    }
  ],
  "recipe": [
    {
      "_id": 101002,
      "id": "white_iron_chunk",
      "name": "Обломок белого железа",
      "amount": 4
    }
  ]
}