{
  "_id": 373200,
  "id": "highflyers_trampoline",
  "rarity": 4,
  "name": "Trampolín de supersaltos",
  "description": "Un trampolín hecho de pergaminos de tela muy resistentes y un marco de metal. Está decorado con patrones característicos de la Bahía de las Olas. Dicen que este trampolín tiene un mecanismo interno especial que lo hace muy elástico, de modo que puede lanzar fácilmente a varios adultos por los aires, e incluso hacer que una persona normal pueda realizar movimientos complicados como volteretas aéreas. Sin embargo, Paimon dice que, tras probar esta decoración, no le pareció que tuviera esas funciones. Tal vez sea porque ella ya puede volar y no necesita un trampolín para hacer esa clase de piruetas.",
  "load": 60,
  "energy": 90,
  "exp": 90,
  "category": [
    {
      "id": 7016,
      "category": "Mecanismo del mundo interior",
      "type": "Exterior"
    }
  ],
  "recipe": [
    {
      "_id": 101002,
      "id": "white_iron_chunk",
      "name": "Pedazo de hierro blanco",
      "amount": 2
    },
    {
      "_id": 101401,
      "id": "fabric",
      "name": "Tela",
      "amount": 10
    }
  ]
}
