{
  "_id": 4,
  "id": "mondstadt_the_city_of_wind_and_song",
  "name": "Mondstadt - Thành phố của gió và những bài ca du mục",
  "order": 9,
  "achievements": [
    {
      "id": 80030,
      "name": "Thám hiểm đại lục - Mondstadt",
      "desc": "Thắp sáng toàn bộ bản đồ Mondstadt (Trừ khu vực Long Tích Tuyết Sơn).",
      "reward": 5,
      "hidden": false,
      "order": 30
    },
    {
      "id": 80031,
      "name": "Ngàn ngọn gió thổi qua",
      "desc": "Mở khoá toàn bộ điểm dịch chuyển ở Mondstadt. (Trừ khu vực Long Tích Tuyết Sơn)",
      "reward": 5,
      "hidden": false,
      "order": 31
    },
    {
      "id": 80032,
      "name": "Lắng nghe tiếng gió",
      "desc": "Hiến tế Thất Thiên Thần Tượng Mondstadt đạt cấp tối đa.",
      "reward": 20,
      "hidden": false,
      "order": 32
    },
    {
      "id": 80033,
      "name": "Thánh đường hành hương - Mondstadt",
      "desc": "Mở phong ấn tất cả Đền Địa Linh ở Mondstadt.",
      "reward": 10,
      "hidden": false,
      "order": 33
    },
    {
      "id": 80034,
      "name": "Người dẫn đường trong gió",
      "desc": "Đuổi theo 10 tiên linh và thắp sáng Đài Tiên Linh ở Mondstadt (Trừ khu vực Long Tích Tuyết Sơn).",
      "reward": 5,
      "hidden": false,
      "order": 34
    },
    {
      "id": 80035,
      "name": "Người dẫn đường trong gió",
      "desc": "Đuổi theo 20 tiên linh và thắp sáng Đài Tiên Linh ở Mondstadt (Trừ khu vực Long Tích Tuyết Sơn).",
      "reward": 10,
      "hidden": false,
      "order": 35,
      "preStage": 80034
    },
    {
      "id": 80036,
      "name": "Người dẫn đường trong gió",
      "desc": "Đuổi theo 40 tiên linh và thắp sáng Đài Tiên Linh ở Mondstadt (Trừ khu vực Long Tích Tuyết Sơn).",
      "reward": 20,
      "hidden": false,
      "order": 36,
      "preStage": 80035
    },
    {
      "id": 80037,
      "name": "Thợ săn kho báu trong gió",
      "desc": "Mở 100 rương báu ở Mondstadt (Trừ khu vực Long Tích Tuyết Sơn).",
      "reward": 5,
      "hidden": false,
      "order": 37
    },
    {
      "id": 80038,
      "name": "Thợ săn kho báu trong gió",
      "desc": "Mở 200 rương báu ở Mondstadt (Trừ khu vực Long Tích Tuyết Sơn).",
      "reward": 10,
      "hidden": false,
      "order": 38,
      "preStage": 80037
    },
    {
      "id": 80039,
      "name": "Thợ săn kho báu trong gió",
      "desc": "Mở 400 rương báu ở Mondstadt (Trừ khu vực Long Tích Tuyết Sơn).",
      "reward": 20,
      "hidden": false,
      "order": 39,
      "preStage": 80038
    },
    {
      "id": 80040,
      "name": "Nhà Mạo Hiểm trong gió",
      "desc": "Tại Mondstadt, hoàn thành 5 khiêu chiến cơ quan Đại Thế Giới trong thời gian quy định (Trừ khu vực Long Tích Tuyết Sơn).",
      "reward": 5,
      "hidden": false,
      "order": 40
    },
    {
      "id": 80041,
      "name": "Nhà Mạo Hiểm trong gió",
      "desc": "Tại Mondstadt, hoàn thành 10 khiêu chiến cơ quan Đại Thế Giới trong thời gian quy định (Trừ khu vực Long Tích Tuyết Sơn).",
      "reward": 10,
      "hidden": false,
      "order": 41,
      "preStage": 80040
    },
    {
      "id": 80042,
      "name": "Nhà Mạo Hiểm trong gió",
      "desc": "Tại Mondstadt, hoàn thành 15 khiêu chiến cơ quan Đại Thế Giới trong thời gian quy định (Trừ khu vực Long Tích Tuyết Sơn).",
      "reward": 20,
      "hidden": false,
      "order": 42,
      "preStage": 80041
    }
  ]
}
