{
  "_id": 362254,
  "id": "maison_cardinalices_lockbox",
  "rarity": 3,
  "name": "Rương Sắt Của Sảnh Chính Luật",
  "description": "Rương chứa đồ trông bình thường nhưng thực chất lại rất đắt tiền, được sản xuất tại Xưởng Beaumont. Nghe nói chiếc rương này có nhiều chức năng như chống va đập, chống sốc, chống thấm nước, chống cháy... Trong những trường hợp đặc biệt, nó không chỉ tự động báo động, mà còn được dùng làm tấm chắn hoặc công cụ để phá cửa sổ. Nhưng thợ của Xưởng Beaumont và nhân viên của Palais Mermonia đều không đưa ra bất kỳ bình luận nào về những tin đồn trên.",
  "load": 85,
  "energy": 60,
  "exp": 60,
  "category": [
    {
      "id": 4002,
      "category": "Phụ kiện",
      "type": "Interior"
    }
  ],
  "recipe": [
    {
      "_id": 101001,
      "id": "iron_chunk",
      "name": "Mảnh Sắt",
      "amount": 4
    },
    {
      "_id": 101002,
      "id": "white_iron_chunk",
      "name": "Mảnh Sắt Trắng",
      "amount": 4
    }
  ]
}
