{
  "_id": 21,
  "id": "meetings_in_outrealm_series_ii",
  "name": "Rencontres dans un autre monde - Partie II",
  "order": 26,
  "achievements": [
    {
      "id": 86021,
      "name": "La folie des grandeurs ne décide pas de l'issue d'un combat",
      "desc": "Affrontez Tartaglia avec l'aide d'un autre joueur.",
      "reward": 10,
      "hidden": false,
      "order": 9014
    },
    {
      "id": 86015,
      "name": "La montagne a bougé",
      "desc": "Affrontez un Géosaure antique avec l'aide d'un autre joueur.",
      "reward": 10,
      "hidden": false,
      "order": 9015
    },
    {
      "id": 86016,
      "name": "Réminiscences",
      "desc": "Affrontez Azhdaha avec l'aide d'un autre joueur.",
      "reward": 10,
      "hidden": false,
      "order": 9016
    },
    {
      "id": 86017,
      "name": "Glace pilée",
      "desc": "Affrontez une Hypostase Cryo avec l'aide d'un autre joueur.",
      "reward": 10,
      "hidden": false,
      "order": 9017
    },
    {
      "id": 86018,
      "name": "Liens brisés",
      "desc": "Affrontez une Lame oni avec l'aide d'un autre joueur.",
      "reward": 10,
      "hidden": false,
      "order": 9018
    },
    {
      "id": 86019,
      "name": "Opération feu de joie",
      "desc": "Affrontez une Hypostase Pyro avec l'aide d'un autre joueur.",
      "reward": 10,
      "hidden": false,
      "order": 9019
    },
    {
      "id": 86020,
      "name": "Pas si perpétuelle que ça...",
      "desc": "Affrontez une Matrice mécanique perpétuelle avec l'aide d'un autre joueur.",
      "reward": 10,
      "hidden": false,
      "order": 9020
    }
  ]
}
