{
  "_id": 22131001,
  "id": "wilderness_hunter",
  "monsterId": 22131001,
  "name": "Cacciatore selvaggio",
  "specialNames": [
    "Cacciatore selvaggio"
  ],
  "investigation": {
    "investigationId": 83,
    "name": "Caccia selvaggia delle terre desolate",
    "categoryType": "Elite",
    "categoryText": "Élite",
    "description": "Un ghoul che vaga tra le lande gelide.\\nUna fitta nebbia nera si diffonde al suo passaggio, e la sua comparsa si dice preluda a calamità ancora maggiori."
  },
  "filename_investigationIcon": "UI_MonsterIcon_WildHunt",
  "rewardPreviewId": 15538,
  "rewardPreview": [
    {
      "_id": 202,
      "id": "mora",
      "name": "Mora"
    },
    {
      "_id": 112136,
      "id": "mistshroud_helmet",
      "name": "Elmo brumoso",
      "count": 0.1751
    },
    {
      "_id": 112135,
      "id": "mistshroud_plate",
      "name": "Frammento di armatura brumoso",
      "count": 0.7003
    },
    {
      "_id": 112134,
      "id": "mistshroud_manifestation",
      "name": "Manifestazione brumosa",
      "count": 2.6263
    },
    {
      "_id": 400023,
      "id": "berserker",
      "name": "Berserker",
      "rarity": 4
    },
    {
      "_id": 400033,
      "id": "instructor",
      "name": "Istruttore",
      "rarity": 4
    },
    {
      "_id": 400043,
      "id": "the_exile",
      "name": "Esule",
      "rarity": 4
    },
    {
      "_id": 400022,
      "id": "berserker",
      "name": "Berserker",
      "rarity": 3
    },
    {
      "_id": 400032,
      "id": "instructor",
      "name": "Istruttore",
      "rarity": 3
    },
    {
      "_id": 400042,
      "id": "the_exile",
      "name": "Esule",
      "rarity": 3
    },
    {
      "_id": 400062,
      "id": "traveling_doctor",
      "name": "Dottoressa errante",
      "rarity": 3
    }
  ],
  "monsterType": "MONSTER_ORDINARY",
  "enemyType": "ELITE",
  "categoryType": "CODEX_SUBTYPE_ABYSS",
  "categoryText": "Abisso",
  "filename_icon": "UI_MonsterIcon_WildHunt_Elite",
  "description": "Un ghoul che si annida tra le lande ghiacciate quando cala l'oscurità. La sua comparsa presagisce l'arrivo di catastrofi indicibili.\\nMolti grandi campioni di un antico regno perduto giacciono sepolti sotto le gelide terre del Nord. Nonostante lo scorrere degli anni abbia cancellato ogni traccia del loro passato, questi nobili spiriti continuano a proteggere la propria dorata terra natia. Risvegliati dall'azione corruttiva dell'Abisso, questi guerrieri considerano ogni trasgressore come una preda da cacciare.",
  "aggroRange": "VISION_LEVEL_NORMAL",
  "bgm": 0,
  "budget": 2,
  "stats": {
    "resistance": {
      "physical": 0.1,
      "pyro": 0.1,
      "dendro": 0.1,
      "hydro": 0.1,
      "geo": 0.1,
      "anemo": 0.1,
      "cryo": 0.1,
      "electro": 0.1
    },
    "base": {
      "hp": 141.2736,
      "attack": 75.36,
      "defense": 500
    },
    "curve": {
      "hp": "GROW_CURVE_HP_2",
      "attack": "GROW_CURVE_ATTACK_2",
      "defense": "GROW_CURVE_DEFENSE"
    }
  }
}