{
  "_id": 104340,
  "id": "philosophies_of_equity",
  "name": "Filosofie di equità",
  "description": "L'equità è il confine della Nazione dell'Acqua.<br/>L'equità è il caposaldo su cui è sorta Fontaine. L'equità richiede il continuo e costante sostegno della moralità e della legge, e la moralità e la legge cambiano costantemente in base al principio immutabile di equità.",
  "source": [],
  "location": "Mondstadt",
  "rarity": 4,
  "craft": {
    "cost": 550,
    "items": [
      {
        "_id": 104339,
        "id": "guide_to_equity",
        "name": "Guida all'equità",
        "amount": 3
      }
    ]
  },
  "domain": "Tenue gloria dimenticata",
  "days": ["Lunedì", "Giovedì", "Domenica"]
}
