{
  "_id": 374835,
  "id": "imaginary_friend_yuegui",
  "rarity": 4,
  "name": "Ami imaginaire « Yuegui »",
  "description": "Une jolie décoration inspirée de Yuegui, l'ami imaginaire de Yaoyao.\\nDepuis que tante Souffle-Nuages a offert Yuegui à Yaoyao, ils sont inséparables. Chaque soir avant de se coucher, Yaoyao borde soigneusement Yuegui sous une petite couverture, ne laissant dépasser que sa tête. Le lendemain matin, la couverture est toujours parfaitement bien rangée, et Yaoyao est persuadée que Yuegui a passé une bonne nuit de sommeil.\\n« Qu'ils soient réels ou imaginaires, c'est toujours agréable de grandir avec des amis à ses côtés. »",
  "load": 40,
  "energy": 90,
  "category": [
    {
      "id": 7015,
      "category": "Éléments spéciaux",
      "type": "Exterior"
    }
  ]
}