{
  "_id": 373215,
  "id": "inspirations_pure_white_blossoms",
  "rarity": 3,
  "name": "Bouquet blanc d'inspiration",
  "description": "Une plante en pot avec un bouquet de fleurs d'un blanc pur que l'on voit couramment à Petrichor. La légende raconte que ces fleurs étaient appréciées et largement cultivées par les habitants du village pour leur élégance et leur beauté. Un dramaturge a même écrit une histoire sur ces fleurs. Dans l'histoire, le protagoniste s'inspire de manière inattendue de ces fleurs blanches pour créer les petites et grandes cloches qui sont désormais utilisées partout à Petrichor.\\nC'est pour cette raison qu'en plus de leur propre signification positive, ces fleurs d'un blanc pur sont également devenues un symbole d'inspiration.",
  "load": 71,
  "energy": 60,
  "exp": 60,
  "category": [
    {
      "id": 7003,
      "category": "Végétation en pot"
    }
  ],
  "recipe": [
    {
      "_id": 101001,
      "id": "iron_chunk",
      "name": "Morceau de fer",
      "amount": 4
    },
    {
      "_id": 101002,
      "id": "white_iron_chunk",
      "name": "Morceau de fer blanc",
      "amount": 4
    }
  ]
}
