{
  "id": "philosophies_of_resistance",
  "name": "Philosophies of \"Resistance\"",
  "description": "Perlawanan adalah tulang punggung Kerajaan Angin.<br/>Sejarah Mondstadt adalah sejarah perlawanan. Rakyat bangkit untuk membiarkan puisi Mondstadt di masa depan bebas seperti angin yang menyebar ke seluruh negeri.",
  "source": ["Didapatkan melalui Craft"],
  "location": "Mondstadt",
  "rarity": 4,
  "craft": {
    "cost": 550,
    "items": [
      {
        "id": "guide_to_resistance",
        "name": "Guide to \"Resistance\"",
        "amount": 3
      }
    ]
  },
  "domain": "Forsaken Rift",
  "days": ["Selasa", "Jumat", "Minggu"]
}
