{
  "_id": 362126,
  "id": "stadiums_spicy_feast_backed_chair",
  "rarity": 3,
  "name": "Seduta con schienale dell'Arena Banchetto piccante",
  "description": "Una seduta in pietra con braccioli e schienale che si trova nell'Arena della Fiamma sacra. Inizialmente, questa seduta era stata pensata per offrire un riposo temporaneo a concorrenti, commentatori e giudici. Pertanto, gli artigiani avevano selezionato delle pietre dalle elevate proprietà termodispersive, in grado di donare una sensazione rinfrescante dopo una giornata faticosa. In seguito si scoprì casualmente che quella \"sensazione refrigerante\" poteva anche alleviare le vampate di calore dovute al consumo di cibo piccante. Così, esse divennero popolari anche in varie attività di ristorazione. Detto questo, sebbene il cibo piccante sia delizioso, andrebbe sempre consumato con moderazione...",
  "load": 85,
  "energy": 60,
  "exp": 60,
  "category": [
    {
      "id": 4001,
      "category": "Seduta",
      "type": "Interior"
    }
  ],
  "recipe": [
    {
      "_id": 101001,
      "id": "iron_chunk",
      "name": "Pezzo di ferro",
      "amount": 4
    },
    {
      "_id": 101002,
      "id": "white_iron_chunk",
      "name": "Pezzo di ferro bianco",
      "amount": 4
    }
  ]
}
