{
  "_id": 373445,
  "id": "the_title_of_champion_is_mine",
  "rarity": 4,
  "name": "\"Il titolo di campionessa è mio!\"",
  "description": "Un aquilone che il viaggiatore ha realizzato sotto la guida di Vestale delle nuvole. Coglie l'espressione trionfale di Paimon, come se stesse dichiarando la vittoria nella gara di aquiloni: \"Muahahahaha! Il titolo di campionessa di volo di aquiloni è mio!\"\\nNon c'è dubbio che un aquilone decorato con un'immagine così bella sia un degno avversario. Ma per evitare equivoci, cerca di non farlo volare all'interno di nessuna città di Fontaine durante i primi tre giorni del mese...",
  "load": 65,
  "energy": 90,
  "category": [
    {
      "id": 7005,
      "category": "Accessorio",
      "type": "Exterior"
    }
  ]
}
