{
  "_id": 331201,
  "id": "elemental_resonance_woven_waters",
  "name": "Resonansi Elemental: Woven Waters",
  "title": "Resonansi Elemental: Woven Waters",
  "desc": "Tarian air memelihara kehidupan.",
  "in_play_description": "",
  "attributes": {
    "cost": 0,
    "card_type": "Kartu Peristiwa",
    "energy": [],
    "tags": ["Resonansi Elemental"]
  },
  "skills": [
    {
      "name": "",
      "desc": "Menciptakan 1 <span style=\"color:#80C0FFFF\">Dadu Hydro</span>.<br/>(Kartu ini hanya dapat ditambahkan jika terdapat minimal 2 Karakter <span style=\"color:#80C0FFFF\">Hydro</span> dalam Dek-mu)"
    }
  ]
}
