{
  "_id": 215111,
  "id": "bullet_trick",
  "shareId": 482,
  "name": "Truque do Projétil",
  "title": "Chasca - Truque do Projétil",
  "desc": "\"Fogo no pavio!\"",
  "in_play_description": "Adiciona 1 carta <span style=\"color:#FFFFFFFF\">Projéteis Caçadores de Sombras</span> à sua Mão.",
  "attributes": {
    "cost": 1,
    "cost_type": "Anemo",
    "card_type": "Carta de Evento",
    "energy": [
      {
        "_id": 1105,
        "id": "anemo",
        "type": "Anemo",
        "count": 1
      }
    ],
    "source": "Recompensa por desafiar Chasca para um duelo na Cauda do Gato e conquistar todos os objetivos de desafio correspondentes",
    "tags": ["Talento"]
  },
  "skills": [
    {
      "name": "",
      "desc": "<span style=\"color:#FFFFFFFF\">Ações Rápidas</span>: Quando seu Personagem em Combate for <span style=\"color:#FFFFFFFF\">Chasca</span>, equipe essa carta. Adiciona 1 carta <span style=\"color:#FFFFFFFF\">Projéteis Caçadores de Sombras</span> à sua Mão.<br/>(Você deve ter Chasca em seu deck para adicionar essa carta a ele)"
    }
  ]
}
