{
  "_id": 370704,
  "id": "deepwood_dwellers_perseverance",
  "rarity": 3,
  "name": "「숲 주민의 집념」",
  "description": "작은 사이즈의 가벼운 텐트. 힘 좋은 성인이라면 한 손으로도 충분히 들어 올릴 수 있고, 심지어는 등에 묶어 휴대하고 다닐 수도 있다. 대신 단기 방수 기능만 갖췄고, 구조가 허술해서 평범한 야수와의 충돌이나 심지어는 나뭇가지에서 뛰어내린 새들로 인해 무너져버릴 수도 있다. 이 텐트에서 밤을 보낼 수 있는 이는 우림에 잠시 쉬어가는 용병처럼 배짱이 두둑한 사람일 것이다. 용병들은 통상 고생을 두려워하지 않고, 늘 건조 식량을 지니고 다니기에 이런 텐트의 물자 보관이 어렵다는 단점은 큰 의미가 없으니 말이다",
  "load": 65,
  "energy": 60,
  "exp": 60,
  "category": [
    {
      "id": 13005,
      "category": "수메르 테마",
      "type": "Exterior"
    }
  ],
  "recipe": [
    {
      "_id": 101315,
      "id": "adhigama_wood",
      "name": "아디가마 나무 원목",
      "amount": 8
    },
    {
      "_id": 101401,
      "id": "fabric",
      "name": "직물",
      "amount": 4
    }
  ]
}
