{
  "_id": 362253,
  "id": "maison_cardinalices_punctuality",
  "rarity": 4,
  "name": "「추기청의 시간」",
  "description": "정확한 폰타인 제작 방식으로 만든 전용 시계. 전적으로 신뢰할 수 있으며, 절대로 잘못된 시간을 표시하지 않는다! 시간을 고의로 빨리 돌리는 걸 방지하기 위해 시계에는 자동 시간 조정 장치가 탑재되어 있으며, 시계는 매일 자동으로 시계 시간을 조정한다. 다만 모든 사람이 이 기능을 좋아하는 건 아닌 듯하다…",
  "load": 64,
  "energy": 90,
  "exp": 90,
  "category": [
    {
      "id": 4002,
      "category": "장식"
    }
  ],
  "recipe": [
    {
      "_id": 101320,
      "id": "ash_wood",
      "name": "물푸레나무 원목",
      "amount": 8
    },
    {
      "_id": 101001,
      "id": "iron_chunk",
      "name": "철광",
      "amount": 8
    }
  ]
}
