{
  "_id": 323005,
  "id": "seed_dispensary",
  "shareId": 312,
  "name": "化种匣",
  "title": "化种匣",
  "desc": "从萍姥姥处获得的神奇匣子。据萍姥姥说，这匣子具有「化种」之能…",
  "in_play_description": "",
  "attributes": {
    "cost": 0,
    "card_type": "支援牌",
    "energy": [],
    "tags": ["道具"]
  },
  "skills": [
    {
      "name": "",
      "desc": "<span style=\"color:#FFFFFFFF\">我方打出原本元素骰费用为1的装备或支援牌时：</span>少花费1个元素骰。（每回合1次）<br/><span style=\"color:#FFFFFFFF\"><span style=\"color:#FFFFFFFF\">可用次数</span>：2</span>"
    }
  ]
}
