{
  "_id": 100015,
  "id": "snapdragon",
  "name": "金鱼草",
  "description": "烹饪后可食用的植株。作为香料能给食材带来奇妙的滋味。",
  "recipes": [
    {
      "_id": 2004,
      "id": "cream_stew",
      "name": "白汁时蔬烩肉"
    },
    {
      "_id": 2103,
      "id": "jewelry_soup",
      "name": "珍珠翡翠白玉汤"
    },
    {
      "_id": 2109,
      "id": "vegetarian_abalone",
      "name": "素鲍鱼"
    },
    {
      "_id": 2113,
      "id": "stirfried_fish_noodles",
      "name": "干炒鱼河"
    },
    {
      "_id": 2209,
      "id": "sangayaki",
      "name": "山家烧"
    },
    {
      "_id": 3113,
      "id": "cured_pork_dry_hotpot",
      "name": "干锅腊肉"
    },
    {
      "_id": 3114,
      "id": "stirfried_shrimp",
      "name": "清炒虾仁"
    },
    {
      "_id": 3118,
      "id": "the_palace_jewels",
      "name": "金玉满堂"
    },
    {
      "_id": 3201,
      "id": "tricolor_dango",
      "name": "三彩团子"
    },
    {
      "_id": 3203,
      "id": "triflavored_skewer",
      "name": "串串三味"
    },
    {
      "_id": 3206,
      "id": "konda_cuisine",
      "name": "绀田煮"
    },
    {
      "_id": 3312,
      "id": "sabz_meat_stew",
      "name": "萨布兹炖肉"
    },
    {
      "_id": 4104,
      "id": "chicken_tofu_pudding",
      "name": "鸡豆花"
    }
  ],
  "source": ["河岸湖泊采集"],
  "rarity": 0
}
