{
  "_id": 322029,
  "id": "forest_blessing",
  "shareId": 502,
  "name": "Segen des Waldes",
  "title": "Segen des Waldes",
  "desc": "„Ich verleihe dir hiermit den Segen des Waldes und schenke dir ein Heim in diesem Land ...“",
  "in_play_description": "",
  "attributes": {
    "cost": 2,
    "cost_type": "Würfel (beliebig)",
    "card_type": "Unterstützungskarte",
    "energy": [
      {
        "_id": 1109,
        "id": "unaligned_element",
        "type": "Würfel (beliebig)",
        "count": 2
      }
    ],
    "tags": [
      "Gefährte"
    ]
  },
  "skills": [
    {
      "name": "",
      "desc": "<span style=\"color:#FFFFFFFF\">Beim Ausspielen dieser Karte oder nach Auslösen von Elementarreaktionen durch deine Figuren:</span> Erschafft zufällig 1 Karte von <span style=\"color:#FFFFFFFF\">Papierflughörnchen</span>, <span style=\"color:#FFFFFFFF\">Papierfrosch</span> und <span style=\"color:#FFFFFFFF\">Papierhamster</span> auf deiner Hand."
    }
  ]
}
