{
  "id": "sacrificial_bow",
  "name": "Sacrificial Bow",
  "description": "A ceremonial hunting bow that has become petrified over time. The trinkets on it are still visible. It grants the wielder the power to withstand the winds of time.",
  "location": "Gacha",
  "type": "Bow",
  "rarity": 4,
  "base": 44,
  "passive": "Composed",
  "bonus": "After dealing damage to an opponent with an Elemental Skill, the skill has a 40% chance to end its own CD. Can only occur once every 30s.",
  "secondary": "Energy Recharge",
  "series": "Sacrificial Series"
}
