{
  "id": "hardwood_weapon_rack",
  "originalId": 373303,
  "rarity": 3,
  "name": "ชั้นวางอาวุธไม้เนื้อแข็ง",
  "description": "ชั้นวางอาวุธสุดคลาสสิก ที่กองทหาร Millelith ใช้กันอย่างแพร่หลาย\\nชั้นวางอาวุธประเภทนี้ มีโครงสร้างที่เรียบง่ายแข็งแรงทนทาน และง่ายต่อการผลิตเป็นชุด ดังนั้นทุกประเทศจึงเริ่มทำการเลียนแบบ\\nแต่ไม้เนื้อแข็งที่กองทหาร Millelith ใช้นั้นมีวิธีการแปรรูปที่สวยงาม และผลิตได้ในเมือง Liyue เท่านั้น ดังนั้นผลิตภัณฑ์เลียนแบบในประเทศอื่น ๆ มักจะด้อยกว่าในเรื่องของประสิทธิภาพ",
  "load": 35,
  "energy": 60,
  "exp": 60,
  "category": [
    {
      "id": 7005,
      "category": "ของตกแต่ง",
      "type": "Exterior"
    }
  ],
  "recipe": [
    {
      "id": "fir_wood",
      "name": "ไม้สนหนาม",
      "amount": 8
    }
  ]
}
