{
  "_id": 374636,
  "id": "puzzlepal_keep_calm_and_carry_on",
  "rarity": 4,
  "name": "คู่หูไขปริศนา - \"จากไปอย่างรีบร้อน\"",
  "description": "ตุ๊กตาผ้าที่สร้างขึ้นโดยมีรุ่นพี่ Faruzan เป็นต้นแบบ ผสมผสานกับตุ๊กตา Floating Hydro Fungus ที่กำลังนิยมในหมู่นักเรียน ภายในติดตั้งกลไกการเดิน การระบุภูมิประเทศ การควบคุมระยะไกล และตรวจจับน้ำหนัก มีฟังก์ชันการทำงานอัตโนมัติที่สมบูรณ์แบบ\\nในฐานะผลลัพธ์จากความร่วมมือระหว่างสมาคมปริศนา และงานสัมมนากลไกโบราณสถาน ตุ๊กตาคู่หูไขปริศนาตัวนี้จึงมีเทคโนโลยีที่ค่อนข้างสูง ขณะเดียวกันนั้น ก็ยังคงรูปลักษณ์ที่มีความน่ารักเอาไว้ แม้จะเดินเข้าไปในโบราณสถานที่มืดตึ๊ดตื๋อ แต่พอได้เห็นตุ๊กตารูปรุ่นพี่ Faruzan ความรู้สึกประหม่าก็จะเบาบางลงได้...",
  "load": 450,
  "energy": 90,
  "exp": 90,
  "category": [
    {
      "id": 7014,
      "category": "สิ่งของชิ้นใหญ่",
      "type": "Exterior"
    }
  ],
  "recipe": [
    {
      "_id": 101002,
      "id": "white_iron_chunk",
      "name": "White Iron Chunk",
      "amount": 4
    },
    {
      "_id": 101401,
      "id": "fabric",
      "name": "ผ้า",
      "amount": 8
    },
    {
      "_id": 101404,
      "id": "blue_dye",
      "name": "สีย้อมสีฟ้า",
      "amount": 4
    }
  ]
}
